hash_cache_venv.py
hash_cache_venv-0.0.0.post0.dist-info/LICENSE
hash_cache_venv-0.0.0.post0.dist-info/WHEEL
hash_cache_venv-0.0.0.post0.dist-info/METADATA
hash_cache_venv-0.0.0.post0.dist-info/RECORD
